codeviz/__init__.py
codeviz/visualizer.py
codeviz-0.1.0.dist-info/METADATA
codeviz-0.1.0.dist-info/WHEEL
codeviz-0.1.0.dist-info/top_level.txt
codeviz-0.1.0.dist-info/RECORD
