Metadata-Version: 2.1
Name: codeviz
Version: 0.1.0
Summary: A code visualization tool
Home-page: https://github.com/PriyankaKatariya/codeviz
Author: Priyanka Katariya
Author-email: priyankatariya.26@gmail.com
License: MIT
Classifier: Programming Language :: Python :: 3
Classifier: License :: OSI Approved :: MIT License
Classifier: Operating System :: OS Independent
Requires-Python: >=3.6
Requires-Dist: matplotlib
